hllama/__init__.py
hllama/json_utils.py
hllama-0.0.7.dist-info/LICENSE
hllama-0.0.7.dist-info/METADATA
hllama-0.0.7.dist-info/WHEEL
hllama-0.0.7.dist-info/top_level.txt
hllama-0.0.7.dist-info/RECORD
