Metadata-Version: 2.1
Name: hllama
Version: 0.0.7
Summary: hllama provides some useful utility functions for LLM.
Home-page: https://github.com/deep-diver/hllama
Author: chansung park
Author-email: deep.diver.csp@gmail.com
Keywords: LLM,Large Language Model,Verification,Utility
Classifier: License :: OSI Approved :: Apache Software License
Classifier: Programming Language :: Python :: 3.8
Classifier: Programming Language :: Python :: 3.9
Classifier: Programming Language :: Python :: 3.10
Classifier: Programming Language :: Python :: 3.11
Requires-Python: >=3.8
License-File: LICENSE
